setup.py
sortieren_von_musik/__init__.py
sortieren_von_musik.egg-info/PKG-INFO
sortieren_von_musik.egg-info/SOURCES.txt
sortieren_von_musik.egg-info/dependency_links.txt
sortieren_von_musik.egg-info/not-zip-safe
sortieren_von_musik.egg-info/top_level.txt