Metadata-Version: 1.0
Name: sortieren-von-musik
Version: 0.1
Summary: Sortieren von Musik
Home-page: UNKNOWN
Author: lbarning
Author-email: lbarning@uni-bremen.de
License: MIT
Platform: UNKNOWN
